xray_protocol_helper/__init__.py
xray_protocol_helper/base64_helper.py
xray_protocol_helper/protocol_helper.py
xray_protocol_helper/xray_json_creator/__init__.py
xray_protocol_helper/xray_json_creator/base_xray_config.py
xray_protocol_helper/xray_json_creator/config_creator.py
xray_protocol_helper/xray_json_creator/config_type.py
xray_protocol_helper/xray_json_creator/consts.py
xray_protocol_helper/xray_json_creator/server_config.py
xray_protocol_helper/xray_json_creator/utils.py
xray_protocol_helper/xray_json_creator/xray_config.py
xray_protocol_helper/xray_json_creator/xray_config_util.py
xray_protocol_helper-0.7.0.dist-info/METADATA
xray_protocol_helper-0.7.0.dist-info/WHEEL
xray_protocol_helper-0.7.0.dist-info/RECORD
