Metadata-Version: 2.3
Name: xray-protocol-helper
Version: 0.7.0
Summary: Helper function for xray protocols
License: MIT
Keywords: xray-protocol-helper
Author: Nobody
Author-email: Nobody@gmail.com
Requires-Python: >=3.11,<4.0
Classifier: License :: OSI Approved :: MIT License
Classifier: Operating System :: OS Independent
Classifier: Programming Language :: Python :: 3
Classifier: Programming Language :: Python :: 3.11
Classifier: Programming Language :: Python :: 3.12
Classifier: Programming Language :: Python :: 3.13
